{
    "entry_1": {
        "AT": 5689.3,
        "BE": 6312.2,
        "BG": 3022.5,
        "CZ": 5428.5,
        "DE": 38421.4,
        "DK": 3226.6,
        "EE": 782.7,
        "EL": 4112.3,
        "ES": 18734.5,
        "FI": 8276.7,
        "FR": 37685.3,
        "HR": 1519.9,
        "HU": 3771.6,
        "IE": 2692.3,
        "IT": 25811.6,
        "LT": 906.1,
        "LU": 533,
        "LV": 651.6,
        "MT": 226.5,
        "NL": 9596.5,
        "PL": 12834.6,
        "PT": 4384.3,
        "RO": 4409.7,
        "SE": 12554.1,
        "SI": 1101.6,
        "SK": 2155.7
    },
    "entry_2": {
        "AT": 5263.3,
        "BE": 5951.8,
        "BG": 2665,
        "CZ": 4824,
        "DE": 36233.7,
        "DK": 2992,
        "EE": 696.8,
        "EL": 4237.9,
        "ES": 18018.6,
        "FI": 7125.5,
        "FR": 34517.3,
        "HR": 1409.6,
        "HU": 3697.5,
        "IE": 2636.4,
        "IT": 26005.6,
        "LT": 874.1,
        "LU": 554.4,
        "LV": 619.6,
        "MT": 242.9,
        "NL": 9601.5,
        "PL": 12383.2,
        "PT": 4461.3,
        "RO": 4190.8,
        "SE": 11202.7,
        "SI": 1117.9,
        "SK": 2001.3
    },
    "entry_3": {

    },
    "entry_4": {
        "AT": 5357.4,
        "BE": 6308.4,
        "BG": 2967.8,
        "CZ": 5466.3,
        "DE": 37318,
        "DK": 3176.3,
        "EE": 773.7,
        "EL": 4002.3,
        "ES": 17860.2,
        "FI": 8004.6,
        "FR": 37917.4,
        "HR": 1364.1,
        "HU": 3791.1,
        "IE": 2731.8,
        "IT": 25201.5,
        "LT": 942.4,
        "LU": 520.1,
        "LV": 659.2,
        "MT": 243.7,
        "NL": 9073.4,
        "PL": 13136.9,
        "PT": 4218.7,
        "RO": 4389,
        "SE": 12921.9,
        "SI": 1037.1,
        "SK": 1994.7
    },
    "entry_5": {
        "AT": 5954.4,
        "BE": 6434.7,
        "BG": 2994,
        "CZ": 5251.6,
        "DE": 36745.9,
        "DK": 3461.6,
        "EE": 829.5,
        "EL": 4329.5,
        "ES": 19664.4,
        "FI": 8652.4,
        "FR": 45581.9,
        "HR": 1411.8,
        "HU": 3889.4,
        "IE": 2891.9,
        "IT": 24965.8,
        "LT": 974.1,
        "LU": 499.3,
        "LV": 689.4,
        "MT": 236.8,
        "NL": 9792.3,
        "PL": 12647.3,
        "PT": 4507.2,
        "RO": 4461,
        "SE": 14057.4,
        "SI": 1093,
        "SK": 2152.1
    }
}

